{
  "hash": "ce296fe5",
  "configHash": "a409d14f",
  "lockfileHash": "22c2f240",
  "browserHash": "5a2c43a9",
  "optimized": {
    "vue": {
      "src": "../../../node_modules/vue/dist/vue.runtime.esm-bundler.js",
      "file": "vue.js",
      "fileHash": "3bd7f15d",
      "needsInterop": false
    },
    "vitepress > @vue/devtools-api": {
      "src": "../../../node_modules/@vue/devtools-api/dist/index.js",
      "file": "vitepress___@vue_devtools-api.js",
      "fileHash": "de2723d9",
      "needsInterop": false
    },
    "vitepress > @vueuse/core": {
      "src": "../../../node_modules/@vueuse/core/index.mjs",
      "file": "vitepress___@vueuse_core.js",
      "fileHash": "d44a3a6d",
      "needsInterop": false
    },
    "vitepress > @vueuse/integrations/useFocusTrap": {
      "src": "../../../node_modules/@vueuse/integrations/useFocusTrap.mjs",
      "file": "vitepress___@vueuse_integrations_useFocusTrap.js",
      "fileHash": "71804838",
      "needsInterop": false
    },
    "vitepress > mark.js/src/vanilla.js": {
      "src": "../../../node_modules/mark.js/src/vanilla.js",
      "file": "vitepress___mark__js_src_vanilla__js.js",
      "fileHash": "221885f2",
      "needsInterop": false
    },
    "vitepress > minisearch": {
      "src": "../../../node_modules/minisearch/dist/es/index.js",
      "file": "vitepress___minisearch.js",
      "fileHash": "0c164e6e",
      "needsInterop": false
    }
  },
  "chunks": {
    "chunk-6F5JWMBQ": {
      "file": "chunk-6F5JWMBQ.js"
    },
    "chunk-VJWGEPT5": {
      "file": "chunk-VJWGEPT5.js"
    }
  }
}